[
    {
        "category": 1, 
        "redirect": "", 
        "description": "冒険ポイントをMAX数値と同等分回復するアイテムです。", 
        "updatedTime": 1618302200, 
        "viewSequence": 1, 
        "closeTime": 1924959599, 
        "name": "冒険ポイント回復アイテム", 
        "startTime": 1577804400, 
        "displayFlag": 1, 
        "itemMstId": 1000
    }, 
    {
        "category": 1, 
        "redirect": "", 
        "description": "討伐ポイントをMAX値まで回復するアイテムです。", 
        "updatedTime": 1618302200, 
        "viewSequence": 2, 
        "closeTime": 1924959599, 
        "name": "討伐ポイント回復アイテム", 
        "startTime": 1577804400, 
        "displayFlag": 1, 
        "itemMstId": 1001
    }, 
    {
        "category": 1, 
        "redirect": "Shop/ShopList", 
        "description": "闘技場の報酬で得られるアイテムです。お店で他のアイテムと交換することができます。", 
        "updatedTime": 1618302200, 
        "viewSequence": 3, 
        "closeTime": 1924959599, 
        "name": "闘技場メダル", 
        "startTime": 1577804400, 
        "displayFlag": 1, 
        "itemMstId": 1002
    }, 
    {
        "category": 1, 
        "redirect": "Shop/ShopList", 
        "description": "キャラクターとお別れした際や報酬等で得られるアイテムです。お店で他のアイテムと交換することができます。", 
        "updatedTime": 1618302200, 
        "viewSequence": 4, 
        "closeTime": 1924959599, 
        "name": "冒険者メダル", 
        "startTime": 1577804400, 
        "displayFlag": 1, 
        "itemMstId": 1003
    }, 
    {
        "category": 1, 
        "redirect": "", 
        "description": "闘技場の陣形強化に必要なアイテムです。", 
        "updatedTime": 1618302200, 
        "viewSequence": 5, 
        "closeTime": 1924959599, 
        "name": "陣形書", 
        "startTime": 1577804400, 
        "displayFlag": 1, 
        "itemMstId": 1004
    }, 
    {
        "category": 1, 
        "redirect": "Quest/QuestChapterList", 
        "description": "1枚消費することでロックがかかった強化のクエストを30分開くことができます。", 
        "updatedTime": 1618302200, 
        "viewSequence": 6, 
        "closeTime": 1924959599, 
        "name": "クエスト依頼書(強化)", 
        "startTime": 1577804400, 
        "displayFlag": 1, 
        "itemMstId": 1005
    }, 
    {
        "category": 1, 
        "redirect": "Quest/QuestChapterList", 
        "description": "1枚消費することでロックがかかった覚醒のクエストを30分開くことができます。", 
        "updatedTime": 1618302200, 
        "viewSequence": 7, 
        "closeTime": 1924959599, 
        "name": "クエスト依頼書(覚醒)", 
        "startTime": 1577804400, 
        "displayFlag": 1, 
        "itemMstId": 1006
    }, 
    {
        "category": 1, 
        "redirect": "Quest/QuestChapterList", 
        "description": "1枚消費することでロックがかかった陣形書のクエストを30分開くことができます。", 
        "updatedTime": 1618302200, 
        "viewSequence": 8, 
        "closeTime": 1924959599, 
        "name": "クエスト依頼書(陣形書)", 
        "startTime": 1577804400, 
        "displayFlag": 1, 
        "itemMstId": 1007
    }, 
    {
        "category": 1, 
        "redirect": "Quest/QuestChapterList", 
        "description": "過去のイベントを開放するのに必要なアイテムです。", 
        "updatedTime": 1618302200, 
        "viewSequence": 9, 
        "closeTime": 1924959599, 
        "name": "イベント開放チケット", 
        "startTime": 1577804400, 
        "displayFlag": 1, 
        "itemMstId": 1008
    }, 
    {
        "category": 3, 
        "redirect": "", 
        "description": "エクスキューショナーの装備と交換できるアイテムです。", 
        "updatedTime": 1618302200, 
        "viewSequence": 9, 
        "closeTime": 1924959599, 
        "name": "彷徨鎧の魂", 
        "startTime": 1577804400, 
        "displayFlag": 1, 
        "itemMstId": 1009
    }, 
    {
        "category": 1, 
        "redirect": "", 
        "description": "エクスキューショナーの上級装備と交換できるアイテムです。", 
        "updatedTime": 1618302200, 
        "viewSequence": 9, 
        "closeTime": 1924959599, 
        "name": "彷徨鎧の怨魂", 
        "startTime": 1577804400, 
        "displayFlag": 1, 
        "itemMstId": 1010
    }, 
    {
        "category": 3, 
        "redirect": "", 
        "description": "レッドフードコブラの装備と交換できるアイテムです。", 
        "updatedTime": 1618302200, 
        "viewSequence": 9, 
        "closeTime": 1924959599, 
        "name": "赤喰大蛇の鱗", 
        "startTime": 1577804400, 
        "displayFlag": 1, 
        "itemMstId": 1011
    }, 
    {
        "category": 1, 
        "redirect": "", 
        "description": "レッドフードコブラの上級装備と交換できるアイテムです。", 
        "updatedTime": 1618302200, 
        "viewSequence": 9, 
        "closeTime": 1924959599, 
        "name": "赤喰大蛇の深紅鱗", 
        "startTime": 1577804400, 
        "displayFlag": 1, 
        "itemMstId": 1012
    }, 
    {
        "category": 3, 
        "redirect": "", 
        "description": "ホワイトファングコブラの装備と交換できるアイテムです。", 
        "updatedTime": 1618302200, 
        "viewSequence": 9, 
        "closeTime": 1924959599, 
        "name": "白牙大蛇の鱗", 
        "startTime": 1577804400, 
        "displayFlag": 1, 
        "itemMstId": 1013
    }, 
    {
        "category": 1, 
        "redirect": "", 
        "description": "ホワイトファングコブラの上級装備と交換できるアイテムです。", 
        "updatedTime": 1618302200, 
        "viewSequence": 9, 
        "closeTime": 1924959599, 
        "name": "白牙大蛇の真珠鱗", 
        "startTime": 1577804400, 
        "displayFlag": 1, 
        "itemMstId": 1014
    }, 
    {
        "category": 3, 
        "redirect": "", 
        "description": "ターミネートボアの装備と交換できるアイテムです。", 
        "updatedTime": 1618302200, 
        "viewSequence": 9, 
        "closeTime": 1924959599, 
        "name": "四腕暴猪の牙", 
        "startTime": 1577804400, 
        "displayFlag": 1, 
        "itemMstId": 1015
    }, 
    {
        "category": 1, 
        "redirect": "", 
        "description": "ターミネートボアの上級装備と交換できるアイテムです。", 
        "updatedTime": 1618302200, 
        "viewSequence": 9, 
        "closeTime": 1924959599, 
        "name": "四腕暴猪の剛牙", 
        "startTime": 1577804400, 
        "displayFlag": 1, 
        "itemMstId": 1016
    }, 
    {
        "category": 3, 
        "redirect": "", 
        "description": "デスクロータイガーの装備と交換できるアイテムです。", 
        "updatedTime": 1618302200, 
        "viewSequence": 9, 
        "closeTime": 1924959599, 
        "name": "死神虎の爪", 
        "startTime": 1577804400, 
        "displayFlag": 1, 
        "itemMstId": 1017
    }, 
    {
        "category": 1, 
        "redirect": "", 
        "description": "デスクロータイガーの上級装備と交換できるアイテムです。", 
        "updatedTime": 1618302200, 
        "viewSequence": 9, 
        "closeTime": 1924959599, 
        "name": "死神虎の鋭爪", 
        "startTime": 1577804400, 
        "displayFlag": 1, 
        "itemMstId": 1018
    }, 
    {
        "category": 3, 
        "redirect": "", 
        "description": "サベージホークの装備と交換できるアイテムです。", 
        "updatedTime": 1618302200, 
        "viewSequence": 9, 
        "closeTime": 1924959599, 
        "name": "荒風鷹の羽", 
        "startTime": 1577804400, 
        "displayFlag": 1, 
        "itemMstId": 1019
    }, 
    {
        "category": 1, 
        "redirect": "", 
        "description": "サベージホークの上級装備と交換できるアイテムです。", 
        "updatedTime": 1618302200, 
        "viewSequence": 9, 
        "closeTime": 1924959599, 
        "name": "荒風鷹の硬羽", 
        "startTime": 1577804400, 
        "displayFlag": 1, 
        "itemMstId": 1020
    }, 
    {
        "category": 3, 
        "redirect": "", 
        "description": "レッドドラゴンの装備と交換できるアイテムです。", 
        "updatedTime": 1618302200, 
        "viewSequence": 9, 
        "closeTime": 1924959599, 
        "name": "赤竜の骨", 
        "startTime": 1577804400, 
        "displayFlag": 1, 
        "itemMstId": 1021
    }, 
    {
        "category": 1, 
        "redirect": "", 
        "description": "レッドドラゴンの上級装備と交換できるアイテムです。", 
        "updatedTime": 1618302200, 
        "viewSequence": 9, 
        "closeTime": 1924959599, 
        "name": "赤竜の炎骨", 
        "startTime": 1577804400, 
        "displayFlag": 1, 
        "itemMstId": 1022
    }, 
    {
        "category": 2, 
        "redirect": "", 
        "description": "キャラクターの覚醒に必要なアイテムです。火属性キャラクターの覚醒に使用します。", 
        "updatedTime": 1618302200, 
        "viewSequence": 1, 
        "closeTime": 1924959599, 
        "name": "入門魔術書[火]", 
        "startTime": 1577804400, 
        "displayFlag": 1, 
        "itemMstId": 2000
    }, 
    {
        "category": 2, 
        "redirect": "", 
        "description": "キャラクターの覚醒に必要なアイテムです。火属性キャラクターの覚醒に使用します。", 
        "updatedTime": 1618302200, 
        "viewSequence": 2, 
        "closeTime": 1924959599, 
        "name": "応用魔術書[火]", 
        "startTime": 1577804400, 
        "displayFlag": 1, 
        "itemMstId": 2001
    }, 
    {
        "category": 2, 
        "redirect": "", 
        "description": "キャラクターの覚醒に必要なアイテムです。火属性キャラクターの覚醒に使用します。", 
        "updatedTime": 1618302200, 
        "viewSequence": 3, 
        "closeTime": 1924959599, 
        "name": "秘伝魔術書[火]", 
        "startTime": 1577804400, 
        "displayFlag": 1, 
        "itemMstId": 2002
    }, 
    {
        "category": 2, 
        "redirect": "", 
        "description": "キャラクターの覚醒に必要なアイテムです。水属性キャラクターの覚醒に使用します。", 
        "updatedTime": 1618302200, 
        "viewSequence": 4, 
        "closeTime": 1924959599, 
        "name": "入門魔術書[水]", 
        "startTime": 1577804400, 
        "displayFlag": 1, 
        "itemMstId": 2010
    }, 
    {
        "category": 2, 
        "redirect": "", 
        "description": "キャラクターの覚醒に必要なアイテムです。水属性キャラクターの覚醒に使用します。", 
        "updatedTime": 1618302200, 
        "viewSequence": 5, 
        "closeTime": 1924959599, 
        "name": "応用魔術書[水]", 
        "startTime": 1577804400, 
        "displayFlag": 1, 
        "itemMstId": 2011
    }, 
    {
        "category": 2, 
        "redirect": "", 
        "description": "キャラクターの覚醒に必要なアイテムです。水属性キャラクターの覚醒に使用します。", 
        "updatedTime": 1618302200, 
        "viewSequence": 6, 
        "closeTime": 1924959599, 
        "name": "秘伝魔術書[水]", 
        "startTime": 1577804400, 
        "displayFlag": 1, 
        "itemMstId": 2012
    }, 
    {
        "category": 2, 
        "redirect": "", 
        "description": "キャラクターの覚醒に必要なアイテムです。風属性キャラクターの覚醒に使用します。", 
        "updatedTime": 1618302200, 
        "viewSequence": 7, 
        "closeTime": 1924959599, 
        "name": "入門魔術書[風]", 
        "startTime": 1577804400, 
        "displayFlag": 1, 
        "itemMstId": 2020
    }, 
    {
        "category": 2, 
        "redirect": "", 
        "description": "キャラクターの覚醒に必要なアイテムです。風属性キャラクターの覚醒に使用します。", 
        "updatedTime": 1618302200, 
        "viewSequence": 8, 
        "closeTime": 1924959599, 
        "name": "応用魔術書[風]", 
        "startTime": 1577804400, 
        "displayFlag": 1, 
        "itemMstId": 2021
    }, 
    {
        "category": 2, 
        "redirect": "", 
        "description": "キャラクターの覚醒に必要なアイテムです。風属性キャラクターの覚醒に使用します。", 
        "updatedTime": 1618302200, 
        "viewSequence": 9, 
        "closeTime": 1924959599, 
        "name": "秘伝魔術書[風]", 
        "startTime": 1577804400, 
        "displayFlag": 1, 
        "itemMstId": 2022
    }, 
    {
        "category": 2, 
        "redirect": "", 
        "description": "キャラクターの覚醒に必要なアイテムです。土属性キャラクターの覚醒に使用します。", 
        "updatedTime": 1618302200, 
        "viewSequence": 10, 
        "closeTime": 1924959599, 
        "name": "入門魔術書[土]", 
        "startTime": 1577804400, 
        "displayFlag": 1, 
        "itemMstId": 2030
    }, 
    {
        "category": 2, 
        "redirect": "", 
        "description": "キャラクターの覚醒に必要なアイテムです。土属性キャラクターの覚醒に使用します。", 
        "updatedTime": 1618302200, 
        "viewSequence": 11, 
        "closeTime": 1924959599, 
        "name": "応用魔術書[土]", 
        "startTime": 1577804400, 
        "displayFlag": 1, 
        "itemMstId": 2031
    }, 
    {
        "category": 2, 
        "redirect": "", 
        "description": "キャラクターの覚醒に必要なアイテムです。土属性キャラクターの覚醒に使用します。", 
        "updatedTime": 1618302200, 
        "viewSequence": 12, 
        "closeTime": 1924959599, 
        "name": "秘伝魔術書[土]", 
        "startTime": 1577804400, 
        "displayFlag": 1, 
        "itemMstId": 2032
    }, 
    {
        "category": 2, 
        "redirect": "", 
        "description": "キャラクターの覚醒に必要なアイテムです。我流キャラクターの覚醒に使用します。", 
        "updatedTime": 1618302200, 
        "viewSequence": 19, 
        "closeTime": 1924959599, 
        "name": "入門実戦書[我流]", 
        "startTime": 1577804400, 
        "displayFlag": 1, 
        "itemMstId": 2060
    }, 
    {
        "category": 2, 
        "redirect": "", 
        "description": "キャラクターの覚醒に必要なアイテムです。我流キャラクターの覚醒に使用します。", 
        "updatedTime": 1618302200, 
        "viewSequence": 20, 
        "closeTime": 1924959599, 
        "name": "応用実戦書[我流]", 
        "startTime": 1577804400, 
        "displayFlag": 1, 
        "itemMstId": 2061
    }, 
    {
        "category": 2, 
        "redirect": "", 
        "description": "キャラクターの覚醒に必要なアイテムです。我流キャラクターの覚醒に使用します。", 
        "updatedTime": 1618302200, 
        "viewSequence": 21, 
        "closeTime": 1924959599, 
        "name": "秘伝実戦書[我流]", 
        "startTime": 1577804400, 
        "displayFlag": 1, 
        "itemMstId": 2062
    }, 
    {
        "category": 2, 
        "redirect": "", 
        "description": "キャラクターの覚醒に必要なアイテムです。剣神流キャラクターの覚醒に使用します。", 
        "updatedTime": 1618302200, 
        "viewSequence": 22, 
        "closeTime": 1924959599, 
        "name": "入門剣術書[剣神流]", 
        "startTime": 1577804400, 
        "displayFlag": 1, 
        "itemMstId": 2070
    }, 
    {
        "category": 2, 
        "redirect": "", 
        "description": "キャラクターの覚醒に必要なアイテムです。剣神流キャラクターの覚醒に使用します。", 
        "updatedTime": 1618302200, 
        "viewSequence": 23, 
        "closeTime": 1924959599, 
        "name": "応用剣術書[剣神流]", 
        "startTime": 1577804400, 
        "displayFlag": 1, 
        "itemMstId": 2071
    }, 
    {
        "category": 2, 
        "redirect": "", 
        "description": "キャラクターの覚醒に必要なアイテムです。剣神流キャラクターの覚醒に使用します。", 
        "updatedTime": 1618302200, 
        "viewSequence": 24, 
        "closeTime": 1924959599, 
        "name": "秘伝剣術書[剣神流]", 
        "startTime": 1577804400, 
        "displayFlag": 1, 
        "itemMstId": 2072
    }, 
    {
        "category": 2, 
        "redirect": "", 
        "description": "キャラクターの覚醒に必要なアイテムです。北神流キャラクターの覚醒に使用します。", 
        "updatedTime": 1618302200, 
        "viewSequence": 25, 
        "closeTime": 1924959599, 
        "name": "入門剣術書[北神流]", 
        "startTime": 1577804400, 
        "displayFlag": 1, 
        "itemMstId": 2080
    }, 
    {
        "category": 2, 
        "redirect": "", 
        "description": "キャラクターの覚醒に必要なアイテムです。北神流キャラクターの覚醒に使用します。", 
        "updatedTime": 1618302200, 
        "viewSequence": 26, 
        "closeTime": 1924959599, 
        "name": "応用剣術書[北神流]", 
        "startTime": 1577804400, 
        "displayFlag": 1, 
        "itemMstId": 2081
    }, 
    {
        "category": 2, 
        "redirect": "", 
        "description": "キャラクターの覚醒に必要なアイテムです。北神流キャラクターの覚醒に使用します。", 
        "updatedTime": 1618302200, 
        "viewSequence": 27, 
        "closeTime": 1924959599, 
        "name": "秘伝剣術書[北神流]", 
        "startTime": 1577804400, 
        "displayFlag": 1, 
        "itemMstId": 2082
    }, 
    {
        "category": 2, 
        "redirect": "", 
        "description": "キャラクターの覚醒に必要なアイテムです。水神流キャラクターの覚醒に使用します。", 
        "updatedTime": 1618302200, 
        "viewSequence": 28, 
        "closeTime": 1924959599, 
        "name": "入門剣術書[水神流]", 
        "startTime": 1577804400, 
        "displayFlag": 1, 
        "itemMstId": 2090
    }, 
    {
        "category": 2, 
        "redirect": "", 
        "description": "キャラクターの覚醒に必要なアイテムです。水神流キャラクターの覚醒に使用します。", 
        "updatedTime": 1618302200, 
        "viewSequence": 29, 
        "closeTime": 1924959599, 
        "name": "応用剣術書[水神流]", 
        "startTime": 1577804400, 
        "displayFlag": 1, 
        "itemMstId": 2091
    }, 
    {
        "category": 2, 
        "redirect": "", 
        "description": "キャラクターの覚醒に必要なアイテムです。水神流キャラクターの覚醒に使用します。", 
        "updatedTime": 1618302200, 
        "viewSequence": 30, 
        "closeTime": 1924959599, 
        "name": "秘伝剣術書[水神流]", 
        "startTime": 1577804400, 
        "displayFlag": 1, 
        "itemMstId": 2092
    }, 
    {
        "category": 2, 
        "redirect": "", 
        "description": "キャラクターの覚醒に必要なアイテムです。全てのキャラクターの覚醒に使用します。", 
        "updatedTime": 1618302200, 
        "viewSequence": 31, 
        "closeTime": 1924959599, 
        "name": "アカシックレコード", 
        "startTime": 1577804400, 
        "displayFlag": 1, 
        "itemMstId": 2100
    }, 
    {
        "category": 3, 
        "redirect": "Shop/ShopList", 
        "description": "お店でイベント限定の商品と交換できるアイテムです。", 
        "updatedTime": 1618302200, 
        "viewSequence": 1, 
        "closeTime": 1621313999, 
        "name": "サラークコイン", 
        "startTime": 1577804400, 
        "displayFlag": 1, 
        "itemMstId": 3000
    }, 
    {
        "category": 1, 
        "redirect": "Shop/ShopList", 
        "description": "イベントショップで様々なアイテムと交換可能", 
        "updatedTime": 1618302200, 
        "viewSequence": 2, 
        "closeTime": 1924959599, 
        "name": "デバッグ用イベントアイテム", 
        "startTime": 1577804400, 
        "displayFlag": 1, 
        "itemMstId": 3001
    }, 
    {
        "category": 1, 
        "redirect": "Shop/ShopList", 
        "description": "イベントクエスト得られるアイテムです。ショップで他のアイテムと交換することができます。", 
        "updatedTime": 1618302200, 
        "viewSequence": 3, 
        "closeTime": 1924959599, 
        "name": "イベント用アイテム3(仮)", 
        "startTime": 1577804400, 
        "displayFlag": 1, 
        "itemMstId": 3002
    }, 
    {
        "category": 4, 
        "redirect": "Footer/GachaTop", 
        "description": "1回ガチャを引くことができます。", 
        "updatedTime": 1618302200, 
        "viewSequence": 1, 
        "closeTime": 1924959599, 
        "name": "ガチャチケット", 
        "startTime": 1577804400, 
        "displayFlag": 1, 
        "itemMstId": 4000
    }, 
    {
        "category": 4, 
        "redirect": "Footer/GachaTop", 
        "description": "★５キャラクターセレクトガチャを引くことができます。", 
        "updatedTime": 1618302200, 
        "viewSequence": 2, 
        "closeTime": 1924959599, 
        "name": "★５セレクトガチャチケット", 
        "startTime": 1577804400, 
        "displayFlag": 1, 
        "itemMstId": 4001
    }, 
    {
        "category": 4, 
        "redirect": "Footer/GachaTop", 
        "description": "★５確定ガチャを引くことができます。", 
        "updatedTime": 1618302200, 
        "viewSequence": 3, 
        "closeTime": 1924959599, 
        "name": "★５確定ガチャチケット", 
        "startTime": 1577804400, 
        "displayFlag": 1, 
        "itemMstId": 4002
    }, 
    {
        "category": 4, 
        "redirect": "Footer/GachaTop", 
        "description": "11回チケットガチャを引くことができます。", 
        "updatedTime": 1618302200, 
        "viewSequence": 4, 
        "closeTime": 1924959599, 
        "name": "11回ガチャチケット", 
        "startTime": 1577804400, 
        "displayFlag": 1, 
        "itemMstId": 4003
    }, 
    {
        "category": 4, 
        "redirect": "Footer/GachaTop", 
        "description": "【祝祭の花嵐】エリス ピックアップガチャの1回ガチャを引くことができます。", 
        "updatedTime": 1618302200, 
        "viewSequence": 1, 
        "closeTime": 1620701999, 
        "name": "【祝祭の花嵐】専用ガチャチケット", 
        "startTime": 1586919600, 
        "displayFlag": 1, 
        "itemMstId": 4004
    }, 
    {
        "category": 5, 
        "redirect": "", 
        "description": "キャラクターのレアリティアップに必要なアイテムです。火属性キャラクターのレアリティアップに使用します。", 
        "updatedTime": 1618302200, 
        "viewSequence": 1, 
        "closeTime": 1924959599, 
        "name": "秘石の欠片[火]", 
        "startTime": 1577804400, 
        "displayFlag": 1, 
        "itemMstId": 5000
    }, 
    {
        "category": 5, 
        "redirect": "", 
        "description": "キャラクターのレアリティアップに必要なアイテムです。火属性キャラクターのレアリティアップに使用します。", 
        "updatedTime": 1618302200, 
        "viewSequence": 2, 
        "closeTime": 1924959599, 
        "name": "秘石[火]", 
        "startTime": 1577804400, 
        "displayFlag": 1, 
        "itemMstId": 5001
    }, 
    {
        "category": 5, 
        "redirect": "", 
        "description": "キャラクターのレアリティアップに必要なアイテムです。火属性キャラクターのレアリティアップに使用します。", 
        "updatedTime": 1618302200, 
        "viewSequence": 3, 
        "closeTime": 1924959599, 
        "name": "秘石の塊[火]", 
        "startTime": 1577804400, 
        "displayFlag": 1, 
        "itemMstId": 5002
    }, 
    {
        "category": 5, 
        "redirect": "", 
        "description": "キャラクターのレアリティアップに必要なアイテムです。水属性キャラクターのレアリティアップに使用します。", 
        "updatedTime": 1618302200, 
        "viewSequence": 4, 
        "closeTime": 1924959599, 
        "name": "秘石の欠片[水]", 
        "startTime": 1577804400, 
        "displayFlag": 1, 
        "itemMstId": 5010
    }, 
    {
        "category": 5, 
        "redirect": "", 
        "description": "キャラクターのレアリティアップに必要なアイテムです。水属性キャラクターのレアリティアップに使用します。", 
        "updatedTime": 1618302200, 
        "viewSequence": 5, 
        "closeTime": 1924959599, 
        "name": "秘石[水]", 
        "startTime": 1577804400, 
        "displayFlag": 1, 
        "itemMstId": 5011
    }, 
    {
        "category": 5, 
        "redirect": "", 
        "description": "キャラクターのレアリティアップに必要なアイテムです。水属性キャラクターのレアリティアップに使用します。", 
        "updatedTime": 1618302200, 
        "viewSequence": 6, 
        "closeTime": 1924959599, 
        "name": "秘石の塊[水]", 
        "startTime": 1577804400, 
        "displayFlag": 1, 
        "itemMstId": 5012
    }, 
    {
        "category": 5, 
        "redirect": "", 
        "description": "キャラクターのレアリティアップに必要なアイテムです。風属性キャラクターのレアリティアップに使用します。", 
        "updatedTime": 1618302200, 
        "viewSequence": 7, 
        "closeTime": 1924959599, 
        "name": "秘石の欠片[風]", 
        "startTime": 1577804400, 
        "displayFlag": 1, 
        "itemMstId": 5020
    }, 
    {
        "category": 5, 
        "redirect": "", 
        "description": "キャラクターのレアリティアップに必要なアイテムです。風属性キャラクターのレアリティアップに使用します。", 
        "updatedTime": 1618302200, 
        "viewSequence": 8, 
        "closeTime": 1924959599, 
        "name": "秘石[風]", 
        "startTime": 1577804400, 
        "displayFlag": 1, 
        "itemMstId": 5021
    }, 
    {
        "category": 5, 
        "redirect": "", 
        "description": "キャラクターのレアリティアップに必要なアイテムです。風属性キャラクターのレアリティアップに使用します。", 
        "updatedTime": 1618302200, 
        "viewSequence": 9, 
        "closeTime": 1924959599, 
        "name": "秘石の塊[風]", 
        "startTime": 1577804400, 
        "displayFlag": 1, 
        "itemMstId": 5022
    }, 
    {
        "category": 5, 
        "redirect": "", 
        "description": "キャラクターのレアリティアップに必要なアイテムです。土属性キャラクターのレアリティアップに使用します。", 
        "updatedTime": 1618302200, 
        "viewSequence": 10, 
        "closeTime": 1924959599, 
        "name": "秘石の欠片[土]", 
        "startTime": 1577804400, 
        "displayFlag": 1, 
        "itemMstId": 5030
    }, 
    {
        "category": 5, 
        "redirect": "", 
        "description": "キャラクターのレアリティアップに必要なアイテムです。土属性キャラクターのレアリティアップに使用します。", 
        "updatedTime": 1618302200, 
        "viewSequence": 11, 
        "closeTime": 1924959599, 
        "name": "秘石[土]", 
        "startTime": 1577804400, 
        "displayFlag": 1, 
        "itemMstId": 5031
    }, 
    {
        "category": 5, 
        "redirect": "", 
        "description": "キャラクターのレアリティアップに必要なアイテムです。土属性キャラクターのレアリティアップに使用します。", 
        "updatedTime": 1618302200, 
        "viewSequence": 12, 
        "closeTime": 1924959599, 
        "name": "秘石の塊[土]", 
        "startTime": 1577804400, 
        "displayFlag": 1, 
        "itemMstId": 5032
    }, 
    {
        "category": 5, 
        "redirect": "", 
        "description": "キャラクターのレアリティアップに必要なアイテムです。我流キャラクターのレアリティアップに使用します。", 
        "updatedTime": 1618302200, 
        "viewSequence": 19, 
        "closeTime": 1924959599, 
        "name": "秘石の欠片[我流]", 
        "startTime": 1577804400, 
        "displayFlag": 1, 
        "itemMstId": 5060
    }, 
    {
        "category": 5, 
        "redirect": "", 
        "description": "キャラクターのレアリティアップに必要なアイテムです。我流キャラクターのレアリティアップに使用します。", 
        "updatedTime": 1618302200, 
        "viewSequence": 20, 
        "closeTime": 1924959599, 
        "name": "秘石[我流]", 
        "startTime": 1577804400, 
        "displayFlag": 1, 
        "itemMstId": 5061
    }, 
    {
        "category": 5, 
        "redirect": "", 
        "description": "キャラクターのレアリティアップに必要なアイテムです。我流キャラクターのレアリティアップに使用します。", 
        "updatedTime": 1618302200, 
        "viewSequence": 21, 
        "closeTime": 1924959599, 
        "name": "秘石の塊[我流]", 
        "startTime": 1577804400, 
        "displayFlag": 1, 
        "itemMstId": 5062
    }, 
    {
        "category": 5, 
        "redirect": "", 
        "description": "キャラクターのレアリティアップに必要なアイテムです。剣神流キャラクターのレアリティアップに使用します。", 
        "updatedTime": 1618302200, 
        "viewSequence": 22, 
        "closeTime": 1924959599, 
        "name": "秘石の欠片[剣神流]", 
        "startTime": 1577804400, 
        "displayFlag": 1, 
        "itemMstId": 5070
    }, 
    {
        "category": 5, 
        "redirect": "", 
        "description": "キャラクターのレアリティアップに必要なアイテムです。剣神流キャラクターのレアリティアップに使用します。", 
        "updatedTime": 1618302200, 
        "viewSequence": 23, 
        "closeTime": 1924959599, 
        "name": "秘石[剣神流]", 
        "startTime": 1577804400, 
        "displayFlag": 1, 
        "itemMstId": 5071
    }, 
    {
        "category": 5, 
        "redirect": "", 
        "description": "キャラクターのレアリティアップに必要なアイテムです。剣神流キャラクターのレアリティアップに使用します。", 
        "updatedTime": 1618302200, 
        "viewSequence": 24, 
        "closeTime": 1924959599, 
        "name": "秘石の塊[剣神流]", 
        "startTime": 1577804400, 
        "displayFlag": 1, 
        "itemMstId": 5072
    }, 
    {
        "category": 5, 
        "redirect": "", 
        "description": "キャラクターのレアリティアップに必要なアイテムです。北神流キャラクターのレアリティアップに使用します。", 
        "updatedTime": 1618302200, 
        "viewSequence": 25, 
        "closeTime": 1924959599, 
        "name": "秘石の欠片[北神流]", 
        "startTime": 1577804400, 
        "displayFlag": 1, 
        "itemMstId": 5080
    }, 
    {
        "category": 5, 
        "redirect": "", 
        "description": "キャラクターのレアリティアップに必要なアイテムです。北神流キャラクターのレアリティアップに使用します。", 
        "updatedTime": 1618302200, 
        "viewSequence": 26, 
        "closeTime": 1924959599, 
        "name": "秘石[北神流]", 
        "startTime": 1577804400, 
        "displayFlag": 1, 
        "itemMstId": 5081
    }, 
    {
        "category": 5, 
        "redirect": "", 
        "description": "キャラクターのレアリティアップに必要なアイテムです。北神流キャラクターのレアリティアップに使用します。", 
        "updatedTime": 1618302200, 
        "viewSequence": 27, 
        "closeTime": 1924959599, 
        "name": "秘石の塊[北神流]", 
        "startTime": 1577804400, 
        "displayFlag": 1, 
        "itemMstId": 5082
    }, 
    {
        "category": 5, 
        "redirect": "", 
        "description": "キャラクターのレアリティアップに必要なアイテムです。水神流キャラクターのレアリティアップに使用します。", 
        "updatedTime": 1618302200, 
        "viewSequence": 28, 
        "closeTime": 1924959599, 
        "name": "秘石の欠片[水神流]", 
        "startTime": 1577804400, 
        "displayFlag": 1, 
        "itemMstId": 5090
    }, 
    {
        "category": 5, 
        "redirect": "", 
        "description": "キャラクターのレアリティアップに必要なアイテムです。水神流キャラクターのレアリティアップに使用します。", 
        "updatedTime": 1618302200, 
        "viewSequence": 29, 
        "closeTime": 1924959599, 
        "name": "秘石[水神流]", 
        "startTime": 1577804400, 
        "displayFlag": 1, 
        "itemMstId": 5091
    }, 
    {
        "category": 5, 
        "redirect": "", 
        "description": "キャラクターのレアリティアップに必要なアイテムです。水神流キャラクターのレアリティアップに使用します。", 
        "updatedTime": 1618302200, 
        "viewSequence": 30, 
        "closeTime": 1924959599, 
        "name": "秘石の塊[水神流]", 
        "startTime": 1577804400, 
        "displayFlag": 1, 
        "itemMstId": 5092
    }, 
    {
        "category": 5, 
        "redirect": "", 
        "description": "キャラクターのレアリティアップに必要なアイテムです。全てのキャラクターのレアリティアップに使用します。", 
        "updatedTime": 1618302200, 
        "viewSequence": 33, 
        "closeTime": 1924959599, 
        "name": "賢者の石", 
        "startTime": 1577804400, 
        "displayFlag": 1, 
        "itemMstId": 5102
    }, 
    {
        "category": 8, 
        "redirect": "", 
        "description": "図書迷宮の扉[上層]を開けるのに必要なアイテムです。", 
        "updatedTime": 1618302200, 
        "viewSequence": 1, 
        "closeTime": 1924959599, 
        "name": "図書迷宮ポイント[上層]", 
        "startTime": 1577804400, 
        "displayFlag": 1, 
        "itemMstId": 8000
    }, 
    {
        "category": 8, 
        "redirect": "", 
        "description": "図書迷宮の扉[中層]を開けるのに必要なアイテムです。", 
        "updatedTime": 1618302200, 
        "viewSequence": 1, 
        "closeTime": 1924959599, 
        "name": "図書迷宮ポイント[中層]", 
        "startTime": 1577804400, 
        "displayFlag": 1, 
        "itemMstId": 8001
    }, 
    {
        "category": 8, 
        "redirect": "", 
        "description": "図書迷宮の扉[下層]を開けるのに必要なアイテムです。", 
        "updatedTime": 1618302200, 
        "viewSequence": 1, 
        "closeTime": 1924959599, 
        "name": "図書迷宮ポイント[下層]", 
        "startTime": 1577804400, 
        "displayFlag": 1, 
        "itemMstId": 8002
    }
]
